ragevals/__init__.py
ragevals/ragevals.py
ragevals/test_ragevals.py
ragevals-0.3.0.dist-info/METADATA
ragevals-0.3.0.dist-info/WHEEL
ragevals-0.3.0.dist-info/top_level.txt
ragevals-0.3.0.dist-info/RECORD
