Metadata-Version: 2.1
Name: ragevals
Version: 0.3.0
Summary: A library for evaluating Retrieval-Augmented Generation (RAG) systems
Home-page: https://github.com/captainawesome78/RAGevals
Author: Shaik Naveed
Author-email: mailmenaveed88@gmail.com
Classifier: Programming Language :: Python :: 3
Classifier: License :: OSI Approved :: MIT License
Classifier: Operating System :: OS Independent
Requires-Python: >=3.10
Requires-Dist: torch
Requires-Dist: sacrebleu
Requires-Dist: rouge-score
Requires-Dist: bert-score
Requires-Dist: transformers
Requires-Dist: nltk
Requires-Dist: textblob
